liffylights.py
setup.cfg
setup.py
liffylights.egg-info/PKG-INFO
liffylights.egg-info/SOURCES.txt
liffylights.egg-info/dependency_links.txt
liffylights.egg-info/top_level.txt